{"frames":{"fishD_12_1.png":{"frame":{"h":201,"idx":0,"w":500,"x":1505,"y":424},"sourceSize":{"h":202,"w":500},"spriteSourceSize":{"x":0,"y":1}},"fishD_12_10.png":{"frame":{"h":239,"idx":0,"w":501,"x":0,"y":0},"sourceSize":{"h":240,"w":502},"spriteSourceSize":{"x":1,"y":1}},"fishD_12_11.png":{"frame":{"h":251,"idx":0,"w":474,"x":502,"y":0},"sourceSize":{"h":252,"w":474},"spriteSourceSize":{"x":0,"y":1}},"fishD_12_12.png":{"frame":{"h":209,"idx":0,"w":469,"x":1470,"y":626},"sourceSize":{"h":210,"w":470},"spriteSourceSize":{"x":1,"y":1}},"fishD_12_13.png":{"frame":{"h":196,"idx":0,"w":470,"x":500,"y":1451},"sourceSize":{"h":196,"w":470},"spriteSourceSize":{"x":0,"y":0}},"fishD_12_14.png":{"frame":{"h":182,"idx":0,"w":466,"x":1471,"y":1020},"sourceSize":{"h":182,"w":466},"spriteSourceSize":{"x":0,"y":0}},"fishD_12_15.png":{"frame":{"h":179,"idx":0,"w":463,"x":1466,"y":1203},"sourceSize":{"h":180,"w":464},"spriteSourceSize":{"x":1,"y":1}},"fishD_12_2.png":{"frame":{"h":202,"idx":0,"w":497,"x":502,"y":466},"sourceSize":{"h":202,"w":498},"spriteSourceSize":{"x":1,"y":0}},"fishD_12_3.png":{"frame":{"h":183,"idx":0,"w":498,"x":1503,"y":836},"sourceSize":{"h":184,"w":498},"spriteSourceSize":{"x":0,"y":1}},"fishD_12_4.png":{"frame":{"h":212,"idx":0,"w":499,"x":0,"y":1159},"sourceSize":{"h":212,"w":500},"spriteSourceSize":{"x":1,"y":0}},"fishD_12_5.png":{"frame":{"h":190,"idx":0,"w":501,"x":502,"y":872},"sourceSize":{"h":190,"w":502},"spriteSourceSize":{"x":1,"y":0}},"fishD_12_6.png":{"frame":{"h":204,"idx":0,"w":502,"x":1004,"y":219},"sourceSize":{"h":204,"w":502},"spriteSourceSize":{"x":0,"y":0}},"fishD_12_7.png":{"frame":{"h":218,"idx":0,"w":498,"x":1476,"y":0},"sourceSize":{"h":218,"w":498},"spriteSourceSize":{"x":0,"y":0}},"fishD_12_8.png":{"frame":{"h":205,"idx":0,"w":499,"x":0,"y":1578},"sourceSize":{"h":206,"w":500},"spriteSourceSize":{"x":1,"y":1}},"fishD_12_9.png":{"frame":{"h":213,"idx":0,"w":501,"x":0,"y":732},"sourceSize":{"h":214,"w":502},"spriteSourceSize":{"x":1,"y":1}},"fishD_13_1.png":{"frame":{"h":201,"idx":0,"w":500,"x":1004,"y":424},"sourceSize":{"h":202,"w":500},"spriteSourceSize":{"x":0,"y":1}},"fishD_13_10.png":{"frame":{"h":239,"idx":0,"w":501,"x":0,"y":240},"sourceSize":{"h":240,"w":502},"spriteSourceSize":{"x":1,"y":1}},"fishD_13_11.png":{"frame":{"h":251,"idx":0,"w":474,"x":0,"y":480},"sourceSize":{"h":252,"w":474},"spriteSourceSize":{"x":0,"y":1}},"fishD_13_12.png":{"frame":{"h":209,"idx":0,"w":469,"x":1000,"y":626},"sourceSize":{"h":210,"w":470},"spriteSourceSize":{"x":1,"y":1}},"fishD_13_13.png":{"frame":{"h":196,"idx":0,"w":470,"x":500,"y":1254},"sourceSize":{"h":196,"w":470},"spriteSourceSize":{"x":0,"y":0}},"fishD_13_14.png":{"frame":{"h":182,"idx":0,"w":466,"x":1004,"y":1020},"sourceSize":{"h":182,"w":466},"spriteSourceSize":{"x":0,"y":0}},"fishD_13_15.png":{"frame":{"h":179,"idx":0,"w":463,"x":1002,"y":1203},"sourceSize":{"h":180,"w":464},"spriteSourceSize":{"x":1,"y":1}},"fishD_13_2.png":{"frame":{"h":202,"idx":0,"w":497,"x":502,"y":669},"sourceSize":{"h":202,"w":498},"spriteSourceSize":{"x":1,"y":0}},"fishD_13_3.png":{"frame":{"h":183,"idx":0,"w":498,"x":1004,"y":836},"sourceSize":{"h":184,"w":498},"spriteSourceSize":{"x":0,"y":1}},"fishD_13_4.png":{"frame":{"h":212,"idx":0,"w":499,"x":0,"y":946},"sourceSize":{"h":212,"w":500},"spriteSourceSize":{"x":1,"y":0}},"fishD_13_5.png":{"frame":{"h":190,"idx":0,"w":501,"x":500,"y":1063},"sourceSize":{"h":190,"w":502},"spriteSourceSize":{"x":1,"y":0}},"fishD_13_6.png":{"frame":{"h":204,"idx":0,"w":502,"x":1507,"y":219},"sourceSize":{"h":204,"w":502},"spriteSourceSize":{"x":0,"y":0}},"fishD_13_7.png":{"frame":{"h":218,"idx":0,"w":498,"x":977,"y":0},"sourceSize":{"h":218,"w":498},"spriteSourceSize":{"x":0,"y":0}},"fishD_13_8.png":{"frame":{"h":205,"idx":0,"w":499,"x":0,"y":1372},"sourceSize":{"h":206,"w":500},"spriteSourceSize":{"x":1,"y":1}},"fishD_13_9.png":{"frame":{"h":213,"idx":0,"w":501,"x":502,"y":252},"sourceSize":{"h":214,"w":502},"spriteSourceSize":{"x":1,"y":1}},"fishD_14_1.png":{"frame":{"h":121,"idx":0,"w":363,"x":1656,"y":1659},"sourceSize":{"h":122,"w":363},"spriteSourceSize":{"x":0,"y":1}},"fishD_14_2.png":{"frame":{"h":137,"idx":0,"w":362,"x":1667,"y":1383},"sourceSize":{"h":138,"w":363},"spriteSourceSize":{"x":0,"y":1}},"fishD_14_3.png":{"frame":{"h":146,"idx":0,"w":354,"x":1312,"y":1383},"sourceSize":{"h":146,"w":355},"spriteSourceSize":{"x":1,"y":0}},"fishD_14_4.png":{"frame":{"h":151,"idx":0,"w":340,"x":500,"y":1648},"sourceSize":{"h":152,"w":341},"spriteSourceSize":{"x":1,"y":1}},"fishD_14_5.png":{"frame":{"h":155,"idx":0,"w":329,"x":1326,"y":1530},"sourceSize":{"h":156,"w":329},"spriteSourceSize":{"x":0,"y":0}},"fishD_14_6.png":{"frame":{"h":151,"idx":0,"w":340,"x":971,"y":1383},"sourceSize":{"h":152,"w":341},"spriteSourceSize":{"x":1,"y":1}},"fishD_14_7.png":{"frame":{"h":146,"idx":0,"w":354,"x":971,"y":1535},"sourceSize":{"h":146,"w":355},"spriteSourceSize":{"x":1,"y":0}},"fishD_14_8.png":{"frame":{"h":137,"idx":0,"w":362,"x":1667,"y":1521},"sourceSize":{"h":138,"w":363},"spriteSourceSize":{"x":0,"y":1}}},"meta":{"image":"res10.png","prefix":"res/fish/res/res10/"}}